<AML>
 <Item type="Action" id="6624DA4AA3E74635ACAE5A9C14FC0CDD" action="add">
  <item_query>&lt;Item type="{@type}" id="{@id}" levels= "1" action="get" /&gt;</item_query>
  <label xml:lang="en">Send Link by E-mail...</label>
 <location>client</location>
  <method keyed_name="Send Link by E-mail" type="Method">
   <Item type="Method" action="get" select="id">
    <name>Send Link by E-mail</name>
   </Item>
  </method>
  <name>Send Link by E-mail</name>
  <target>none</target>
  <type>item</type>
 </Item>
</AML>